{"53":{"Type":"upgrade_unit_ingame","Time":"13 13.699397563934326","Pos":"Hidoh (Deathless Reaper) - 1"},"43":{"Type":"upgrade_unit_ingame","Time":"11 11.063268661499023","Pos":"Kurimi (Time Queen) - 3"},"73":{"Type":"upgrade_unit_ingame","Time":"18 13.450531959533691","Pos":"Hidoh (Deathless Reaper) - 2"},"63":{"Type":"upgrade_unit_ingame","Time":"15 14.866333246231079","Pos":"Dracula (Vampire King) - 1"},"47":{"Type":"upgrade_unit_ingame","Time":"12 15.466787815093994","Pos":"Dracula (Vampire King) - 1"},"37":{"Type":"spawn_unit","Time":"10 3.995468854904175","Dir":"0.5841812491416931, -0.7235525250434875, -0.3677009046077728","Rot":0,"Unit":"Dracula (Vampire King)","Pos":"-147.45272827148438, 80.2786636352539, 79.48982238769531"},"67":{"Type":"spawn_unit","Time":"17 15.714689493179321","Dir":"0.8335950970649719, -0.5021631121635437, 0.23011194169521332","Rot":0,"Unit":"Hidoh (Deathless Reaper)","Pos":"-136.82655334472656, 80.92334747314453, 56.45915603637695"},"57":{"Type":"upgrade_unit_ingame","Time":"14 13.702059745788574","Pos":"Hidoh (Deathless Reaper) - 1"},"27":{"Type":"upgrade_unit_ingame","Time":"7 8.58763337135315","Pos":"Speedcart - 3"},"17":{"Type":"upgrade_unit_ingame","Time":"5 6.735340356826782","Pos":"Speedcart - 1"},"13":{"Type":"spawn_unit","Time":"5 2.4326205253601074","Dir":"0.8326517939567566, -0.3719729483127594, -0.41027697920799255","Rot":0,"Unit":"Kurimi (Time Queen)","Pos":"-145.725341796875, 78.12277221679688, 74.94066619873047"},"33":{"Time":"9 9.060383319854736","Type":"vote_wave_skip"},"23":{"Type":"upgrade_unit_ingame","Time":"7 4.572675943374634","Pos":"Loid - 1"},"42":{"Time":"11 11.00825548171997","Type":"vote_wave_skip"},"52":{"Time":"13 12.965202331542969","Type":"vote_wave_skip"},"62":{"Type":"upgrade_unit_ingame","Time":"15 14.83790397644043","Pos":"Dracula (Vampire King) - 1"},"72":{"Type":"upgrade_unit_ingame","Time":"18 9.141841173171997","Pos":"Hidoh (Deathless Reaper) - 2"},"36":{"Type":"upgrade_unit_ingame","Time":"9 9.280922889709473","Pos":"Kurimi (Time Queen) - 3"},"46":{"Type":"upgrade_unit_ingame","Time":"12 15.356336116790771","Pos":"Dracula (Vampire King) - 1"},"56":{"Type":"upgrade_unit_ingame","Time":"14 13.667943716049194","Pos":"Hidoh (Deathless Reaper) - 1"},"66":{"Type":"upgrade_unit_ingame","Time":"17 5.967615604400635","Pos":"Loid - 1"},"16":{"Type":"upgrade_unit_ingame","Time":"5 6.5940728187561035","Pos":"Speedcart - 1"},"26":{"Type":"upgrade_unit_ingame","Time":"7 7.347408771514893","Pos":"Speedcart - 3"},"12":{"Time":"4 4.996948480606079","Type":"vote_wave_skip"},"22":{"Type":"upgrade_unit_ingame","Time":"6 6.141296625137329","Pos":"Speedcart - 2"},"32":{"Type":"spawn_unit","Time":"9 4.006914138793945","Dir":"0.8876954317092896, -0.460417777299881, 0.003503857646137476","Rot":0,"Unit":"Dracula (Vampire King)","Pos":"-146.70907592773438, 80.22168731689453, 67.0414810180664"},"71":{"Type":"upgrade_unit_ingame","Time":"18 6.643693685531616","Pos":"Dracula (Vampire King) - 1"},"61":{"Time":"15 14.714490175247192","Type":"vote_wave_skip"},"51":{"Type":"spawn_unit","Time":"13 11.920772790908813","Dir":"0.16171537339687347, -0.40159663558006287, 0.9014257192611694","Rot":0,"Unit":"Hidoh (Deathless Reaper)","Pos":"-151.16217041015625, 79.21524810791016, 104.89834594726562"},"41":{"Type":"upgrade_unit_ingame","Time":"10 10.233379602432251","Pos":"Kurimi (Time Queen) - 3"},"65":{"Type":"upgrade_unit_ingame","Time":"16 16.136367559432983","Pos":"Dracula (Vampire King) - 1"},"55":{"Type":"upgrade_unit_ingame","Time":"14 13.516167879104614","Pos":"Hidoh (Deathless Reaper) - 1"},"45":{"Time":"12 12.000058650970459","Type":"vote_wave_skip"},"35":{"Type":"upgrade_unit_ingame","Time":"9 9.278790473937988","Pos":"Kurimi (Time Queen) - 3"},"59":{"Type":"upgrade_unit_ingame","Time":"14 14.242894887924194","Pos":"Hidoh (Deathless Reaper) - 1"},"49":{"Type":"upgrade_unit_ingame","Time":"12 15.53824496269226","Pos":"Dracula (Vampire King) - 1"},"39":{"Type":"upgrade_unit_ingame","Time":"10 10.161547422409058","Pos":"Kurimi (Time Queen) - 3"},"29":{"Time":"8 7.948798179626465","Type":"vote_wave_skip"},"79":{"Time":"19 18.994298696517944","Type":"vote_wave_skip"},"69":{"Type":"upgrade_unit_ingame","Time":"17 17.17928433418274","Pos":"Dracula (Vampire King) - 1"},"1":{"Type":"spawn_unit","Time":"0 2.978893995285034","Dir":"0.3084262013435364, -0.9470427632331848, 0.08934876322746277","Rot":0,"Unit":"Speedcart","Pos":"-141.848388671875, 81.27488708496094, 80.89799499511719"},"3":{"Type":"spawn_unit","Time":"1 8.466768980026245","Dir":"0.23934729397296906, -0.935681939125061, -0.25925344228744507","Rot":0,"Unit":"Speedcart","Pos":"-141.85560607910156, 81.27523803710938, 80.86018371582031"},"2":{"Time":"1 4.376999855041504","Type":"vote_wave_skip"},"19":{"Time":"6 6.037216663360596","Type":"vote_wave_skip"},"4":{"Type":"spawn_unit","Time":"2 3.927380084991455","Dir":"0.5086830854415894, -0.5219766497612, -0.684676468372345","Rot":0,"Unit":"Kurimi (Time Queen)","Pos":"-142.65997314453125, 81.1662368774414, 87.60787200927734"},"7":{"Type":"spawn_unit","Time":"2 9.18959379196167","Dir":"0.4497913718223572, -0.761940598487854, -0.46597665548324585","Rot":0,"Unit":"Loid","Pos":"-142.66868591308594, 81.1445083618164, 87.63382720947266"},"6":{"Type":"spawn_unit","Time":"2 6.54810643196106","Dir":"0.5509117841720581, -0.7919783592224121, -0.26318493485450745","Rot":0,"Unit":"Speedcart","Pos":"-142.6544952392578, 81.1358871459961, 87.65267944335938"},"25":{"Type":"upgrade_unit_ingame","Time":"7 7.129751443862915","Pos":"Speedcart - 2"},"15":{"Time":"5 5.151709318161011","Type":"vote_wave_skip"},"31":{"Type":"upgrade_unit_ingame","Time":"8 8.064582824707031","Pos":"Loid - 1"},"21":{"Type":"upgrade_unit_ingame","Time":"6 6.1407551765441895","Pos":"Speedcart - 2"},"11":{"Type":"upgrade_unit_ingame","Time":"3 5.866463899612427","Pos":"Speedcart - 3"},"60":{"Type":"upgrade_unit_ingame","Time":"14 14.324322700500488","Pos":"Hidoh (Deathless Reaper) - 1"},"70":{"Type":"sell_unit_ingame","Time":"18 6.435211181640625","Pos":"Hidoh (Deathless Reaper) - 1"},"40":{"Type":"upgrade_unit_ingame","Time":"10 10.232524633407593","Pos":"Kurimi (Time Queen) - 3"},"50":{"Type":"upgrade_unit_ingame","Time":"12 15.554534196853638","Pos":"Dracula (Vampire King) - 1"},"54":{"Type":"upgrade_unit_ingame","Time":"14 13.377512693405151","Pos":"Hidoh (Deathless Reaper) - 1"},"64":{"Time":"16 15.965360879898071","Type":"vote_wave_skip"},"34":{"Type":"upgrade_unit_ingame","Time":"9 9.155032634735107","Pos":"Loid - 1"},"44":{"Type":"upgrade_unit_ingame","Time":"11 11.202048063278198","Pos":"Kurimi (Time Queen) - 3"},"48":{"Type":"upgrade_unit_ingame","Time":"12 15.533793210983276","Pos":"Dracula (Vampire King) - 1"},"58":{"Time":"14 14.113279581069946","Type":"vote_wave_skip"},"28":{"Type":"upgrade_unit_ingame","Time":"8 7.678660869598389","Pos":"Loid - 1"},"38":{"Time":"10 10.037173748016357","Type":"vote_wave_skip"},"84":{"Type":"sell_unit_ingame","Time":"20 4.3115761280059814","Pos":"Speedcart - 3"},"8":{"Type":"upgrade_unit_ingame","Time":"3 3.5478646755218506","Pos":"Speedcart - 1"},"68":{"Time":"17 17.031266689300537","Type":"vote_wave_skip"},"78":{"Type":"upgrade_unit_ingame","Time":"18 19.901695489883423","Pos":"Hidoh (Deathless Reaper) - 2"},"82":{"Type":"sell_unit_ingame","Time":"20 1.7339613437652588","Pos":"Speedcart - 1"},"81":{"Type":"upgrade_unit_ingame","Time":"19 19.111207008361816","Pos":"Hidoh (Deathless Reaper) - 2"},"9":{"Time":"3 5.004561901092529","Type":"vote_wave_skip"},"5":{"Time":"2 5.030211448669434","Type":"vote_wave_skip"},"76":{"Type":"upgrade_unit_ingame","Time":"18 17.984082460403442","Pos":"Hidoh (Deathless Reaper) - 2"},"18":{"Type":"upgrade_unit_ingame","Time":"5 6.858732223510742","Pos":"Speedcart - 1"},"75":{"Type":"upgrade_unit_ingame","Time":"18 17.974865198135376","Pos":"Hidoh (Deathless Reaper) - 2"},"74":{"Time":"18 17.905294179916382","Type":"vote_wave_skip"},"14":{"Type":"spawn_unit","Time":"5 4.833569765090942","Dir":"0.7982889413833618, -0.4480558931827545, -0.4024684429168701","Rot":0,"Unit":"Kurimi (Time Queen)","Pos":"-145.73007202148438, 78.11557006835938, 74.94206237792969"},"24":{"Time":"7 7.031426906585693","Type":"vote_wave_skip"},"77":{"Type":"upgrade_unit_ingame","Time":"18 17.98479390144348","Pos":"Hidoh (Deathless Reaper) - 2"},"80":{"Type":"upgrade_unit_ingame","Time":"19 19.102465867996216","Pos":"Hidoh (Deathless Reaper) - 2"},"20":{"Type":"upgrade_unit_ingame","Time":"6 6.132380723953247","Pos":"Speedcart - 2"},"30":{"Type":"upgrade_unit_ingame","Time":"8 8.056588172912598","Pos":"Loid - 1"},"83":{"Type":"sell_unit_ingame","Time":"20 2.85416316986084","Pos":"Speedcart - 2"},"10":{"Type":"upgrade_unit_ingame","Time":"3 5.696118593215942","Pos":"Speedcart - 3"}}