{"53":{"Type":"upgrade_unit_ingame","Time":"13 13.266809940338135","Pos":"Getu (Master of Curses) - 1"},"43":{"Type":"upgrade_unit_ingame","Time":"10 10.31558632850647","Pos":"Igrith (Blood Commander) - 1"},"51":{"Type":"upgrade_unit_ingame","Time":"13 3.9060261249542236","Pos":"Getu (Master of Curses) - 1"},"41":{"Type":"upgrade_unit_ingame","Time":"10 10.308899879455566","Pos":"Igrith (Blood Commander) - 1"},"47":{"Type":"upgrade_unit_ingame","Time":"11 11.220071077346802","Pos":"Igrith (Blood Commander) - 1"},"37":{"Type":"upgrade_unit_ingame","Time":"9 9.676867008209229","Pos":"Speedcart - 3"},"45":{"Time":"11 10.989777326583862","Type":"vote_wave_skip"},"35":{"Type":"upgrade_unit_ingame","Time":"9 9.554935693740845","Pos":"Speedcart - 3"},"59":{"Type":"upgrade_unit_ingame","Time":"15 15.31740927696228","Pos":"Getu (Master of Curses) - 1"},"49":{"Type":"upgrade_unit_ingame","Time":"12 12.633825540542603","Pos":"Igrith (Blood Commander) - 1"},"39":{"Type":"upgrade_unit_ingame","Time":"9 11.79083800315857","Pos":"Igrith (Blood Commander) - 1"},"29":{"Type":"upgrade_unit_ingame","Time":"8 8.265603303909302","Pos":"Loid - 1"},"10":{"Time":"3 5.0152928829193115","Type":"vote_wave_skip"},"60":{"Time":"16 15.98932933807373","Type":"vote_wave_skip"},"1":{"Type":"spawn_unit","Time":"0 39.6220006942749","Dir":"-0.645950198173523, -0.7611917853355408, 0.05775313824415207","Rot":0,"Unit":"Speedcart","Pos":"-141.49798583984375, 85.65120697021484, 305.4068298339844"},"12":{"Type":"upgrade_unit_ingame","Time":"3 9.836010932922363","Pos":"Speedcart - 1"},"3":{"Time":"1 5.0125672817230225","Type":"vote_wave_skip"},"2":{"Type":"spawn_unit","Time":"1 0.7748653888702393","Dir":"-0.635009229183197, -0.7476398348808289, 0.1944165974855423","Rot":0,"Unit":"Loid","Pos":"-141.49801635742188, 85.65125274658203, 305.42095947265625"},"5":{"Type":"spawn_unit","Time":"1 8.631770610809326","Dir":"-0.5796136856079102, -0.691757321357727, 0.43072018027305603","Rot":0,"Unit":"Speedcart","Pos":"-141.49740600585938, 85.65091705322266, 305.4490051269531"},"4":{"Type":"spawn_unit","Time":"1 5.898245334625244","Dir":"-0.6208189129829407, -0.7213026285171509, 0.30709365010261536","Rot":0,"Unit":"Speedcart","Pos":"-141.49855041503906, 85.6516342163086, 305.43353271484375"},"7":{"Type":"spawn_unit","Time":"2 5.760367393493652","Dir":"-0.4760841429233551, -0.636520266532898, -0.6067832708358765","Rot":0,"Unit":"Igrith (Blood Commander)","Pos":"-141.49290466308594, 85.64767456054688, 305.3244323730469"},"6":{"Time":"2 5.001633882522583","Type":"vote_wave_skip"},"9":{"Type":"upgrade_unit_ingame","Time":"3 4.402226686477661","Pos":"Loid - 1"},"8":{"Type":"spawn_unit","Time":"2 8.617265224456787","Dir":"-0.5575517416000366, -0.6490648984909058, 0.5175428986549377","Rot":0,"Unit":"AI (Idol)","Pos":"-141.49842834472656, 85.651611328125, 305.4619140625"},"27":{"Type":"upgrade_unit_ingame","Time":"8 2.9451160430908203","Pos":"Speedcart - 1"},"17":{"Time":"5 5.007621765136719","Type":"vote_wave_skip"},"13":{"Type":"upgrade_unit_ingame","Time":"4 0.6971235275268555","Pos":"Speedcart - 2"},"21":{"Type":"upgrade_unit_ingame","Time":"6 6.242138862609863","Pos":"Loid - 1"},"11":{"Type":"upgrade_unit_ingame","Time":"3 5.561490774154663","Pos":"AI (Idol) - 1"},"23":{"Type":"upgrade_unit_ingame","Time":"7 0.053258419036865234","Pos":"Speedcart - 2"},"42":{"Type":"upgrade_unit_ingame","Time":"10 10.315069198608398","Pos":"Igrith (Blood Commander) - 1"},"52":{"Time":"13 12.97955584526062","Type":"vote_wave_skip"},"62":{"Type":"upgrade_unit_ingame","Time":"17 17.367517709732056","Pos":"Getu (Master of Curses) - 1"},"50":{"Type":"upgrade_unit_ingame","Time":"13 3.8301687240600586","Pos":"Getu (Master of Curses) - 1"},"36":{"Type":"upgrade_unit_ingame","Time":"9 9.559266090393066","Pos":"Speedcart - 3"},"46":{"Type":"upgrade_unit_ingame","Time":"11 11.21364712715149","Pos":"Igrith (Blood Commander) - 1"},"34":{"Type":"upgrade_unit_ingame","Time":"9 9.28170919418335","Pos":"Loid - 1"},"44":{"Type":"upgrade_unit_ingame","Time":"11 1.6119470596313477","Pos":"Igrith (Blood Commander) - 1"},"48":{"Time":"12 12.226260662078857","Type":"vote_wave_skip"},"58":{"Time":"15 15.05722975730896","Type":"vote_wave_skip"},"28":{"Time":"8 8.018377780914307","Type":"vote_wave_skip"},"38":{"Type":"upgrade_unit_ingame","Time":"9 11.493880271911621","Pos":"Igrith (Blood Commander) - 1"},"57":{"Type":"upgrade_unit_ingame","Time":"14 14.370213031768799","Pos":"Getu (Master of Curses) - 1"},"56":{"Time":"14 14.086620092391968","Type":"vote_wave_skip"},"55":{"Type":"cycle_priority","Prio":"Last","Time":"14 11.523091316223145","Pos":"Igrith (Blood Commander) - 1"},"54":{"Type":"upgrade_unit_ingame","Time":"13 13.275803327560425","Pos":"Getu (Master of Curses) - 1"},"33":{"Time":"9 9.040130853652954","Type":"vote_wave_skip"},"25":{"Type":"upgrade_unit_ingame","Time":"7 7.250661373138428","Pos":"Loid - 1"},"19":{"Type":"upgrade_unit_ingame","Time":"6 1.2203786373138428","Pos":"Speedcart - 3"},"40":{"Time":"10 10.050301790237427","Type":"vote_wave_skip"},"15":{"Type":"upgrade_unit_ingame","Time":"4 5.275071620941162","Pos":"AI (Idol) - 1"},"18":{"Type":"upgrade_unit_ingame","Time":"5 5.2530012130737305","Pos":"AI (Idol) - 1"},"31":{"Type":"upgrade_unit_ingame","Time":"8 12.045149326324463","Pos":"Speedcart - 2"},"61":{"Time":"17 17.05544424057007","Type":"vote_wave_skip"},"14":{"Time":"4 5.02623724937439","Type":"vote_wave_skip"},"24":{"Time":"7 7.0114967823028564","Type":"vote_wave_skip"},"16":{"Type":"upgrade_unit_ingame","Time":"4 8.396903276443481","Pos":"Speedcart - 1"},"26":{"Type":"spawn_unit","Time":"7 10.972053527832031","Dir":"-0.6747626066207886, -0.7279084920883179, -0.12183961272239685","Rot":0,"Unit":"Getu (Master of Curses)","Pos":"-138.57801818847656, 85.79983520507812, 296.6595764160156"},"20":{"Time":"6 6.001937389373779","Type":"vote_wave_skip"},"30":{"Type":"upgrade_unit_ingame","Time":"8 10.515897750854492","Pos":"Speedcart - 1"},"22":{"Type":"upgrade_unit_ingame","Time":"6 6.253263235092163","Pos":"Loid - 1"},"32":{"Type":"upgrade_unit_ingame","Time":"9 0.8746240139007568","Pos":"Speedcart - 2"}}